lign/__init__.py
lign/graph.py
lign/nn.py
lign/test.py
lign/train.py
lign/models/CIFAR.py
lign/models/CORA.py
lign/models/MNIST.py
lign/models/__init__.py
lign/utils/__init__.py
lign/utils/clustering.py
lign/utils/functions.py
lign/utils/g_types.py
lign/utils/io.py
lign/utils/load.py
lign/utils/defaults/graph.lign
lign-0.1.1.dist-info/LICENSE
lign-0.1.1.dist-info/METADATA
lign-0.1.1.dist-info/WHEEL
lign-0.1.1.dist-info/top_level.txt
lign-0.1.1.dist-info/RECORD
