Metadata-Version: 2.1
Name: lign
Version: 0.1.1
Summary: A framework for working with graphs alongside PyTorch
Home-page: https://github.com/JosueCom/Lign
Author: Josue N Rivera
Author-email: josue.n.rivera@outlook.com
License: Mozilla Public License Version 2.0
Platform: UNKNOWN
Requires-Python: >=3.7.0
Requires-Dist: torch
Requires-Dist: torchvision
Requires-Dist: numpy
Requires-Dist: pandas
Requires-Dist: future
